exceptions.py
kestra.py
kestra-1.1.0.dist-info/METADATA
kestra-1.1.0.dist-info/WHEEL
kestra-1.1.0.dist-info/top_level.txt
kestra-1.1.0.dist-info/RECORD
