Metadata-Version: 2.4
Name: kestra
Version: 1.1.0
Summary: Kestra is an infinitely scalable orchestration and scheduling platform, creating, running, scheduling, and monitoring millions of complex pipelines.
Home-page: https://kestra.io
Author: Kestra
Author-email: hello@kestra.io
License: Apache License 2.0
Project-URL: Source, https://github.com/kestra-io/libs
Project-URL: Tracker, https://github.com/kestra-io/libs/issues
Platform: any
Classifier: License :: OSI Approved :: Apache Software License
Classifier: Programming Language :: Python
Classifier: Programming Language :: Python :: 3
Requires-Python: >=3
Requires-Dist: requests
Requires-Dist: amazon.ion
Requires-Dist: python-dateutil
Provides-Extra: test
Requires-Dist: pytest; extra == "test"
Requires-Dist: requests_mock; extra == "test"
Requires-Dist: pytest-mock; extra == "test"
Provides-Extra: dev
Requires-Dist: isort; extra == "dev"
Requires-Dist: black; extra == "dev"
Requires-Dist: flake8; extra == "dev"
Dynamic: author
Dynamic: author-email
Dynamic: classifier
Dynamic: description
Dynamic: description-content-type
Dynamic: home-page
Dynamic: license
Dynamic: platform
Dynamic: project-url
Dynamic: provides-extra
Dynamic: requires-dist
Dynamic: requires-python
Dynamic: summary
